vectorkit/__init__.py
vectorkit/vectortools.py
vectorkit-0.1.9.dist-info/LICENSE
vectorkit-0.1.9.dist-info/METADATA
vectorkit-0.1.9.dist-info/WHEEL
vectorkit-0.1.9.dist-info/entry_points.txt
vectorkit-0.1.9.dist-info/top_level.txt
vectorkit-0.1.9.dist-info/RECORD
